openleadr/__init__.py
openleadr/client.py
openleadr/enums.py
openleadr/errors.py
openleadr/fingerprint.py
openleadr/hooks.py
openleadr/messaging.py
openleadr/objects.py
openleadr/preflight.py
openleadr/server.py
openleadr/utils.py
openleadr/schema/LICENSES.txt
openleadr/schema/oadr_20b.xsd
openleadr/schema/oadr_ISO_ISO3AlphaCurrencyCode_20100407.xsd
openleadr/schema/oadr_atom.xsd
openleadr/schema/oadr_ei_20b.xsd
openleadr/schema/oadr_emix_20b.xsd
openleadr/schema/oadr_gml_20b.xsd
openleadr/schema/oadr_greenbutton.xsd
openleadr/schema/oadr_power_20b.xsd
openleadr/schema/oadr_pyld_20b.xsd
openleadr/schema/oadr_siscale_20b.xsd
openleadr/schema/oadr_strm_20b.xsd
openleadr/schema/oadr_xcal_20b.xsd
openleadr/schema/oadr_xml.xsd
openleadr/schema/oadr_xmldsig-properties-schema.xsd
openleadr/schema/oadr_xmldsig.xsd
openleadr/schema/oadr_xmldsig11.xsd
openleadr/service/__init__.py
openleadr/service/decorators.py
openleadr/service/event_service.py
openleadr/service/opt_service.py
openleadr/service/poll_service.py
openleadr/service/registration_service.py
openleadr/service/report_service.py
openleadr/service/vtn_service.py
openleadr/templates/oadrCancelOpt.xml
openleadr/templates/oadrCancelPartyRegistration.xml
openleadr/templates/oadrCancelReport.xml
openleadr/templates/oadrCanceledOpt.xml
openleadr/templates/oadrCanceledPartyRegistration.xml
openleadr/templates/oadrCanceledReport.xml
openleadr/templates/oadrCreateOpt.xml
openleadr/templates/oadrCreatePartyRegistration.xml
openleadr/templates/oadrCreateReport.xml
openleadr/templates/oadrCreatedEvent.xml
openleadr/templates/oadrCreatedOpt.xml
openleadr/templates/oadrCreatedPartyRegistration.xml
openleadr/templates/oadrCreatedReport.xml
openleadr/templates/oadrDistributeEvent.xml
openleadr/templates/oadrPayload.xml
openleadr/templates/oadrPoll.xml
openleadr/templates/oadrQueryRegistration.xml
openleadr/templates/oadrRegisterReport.xml
openleadr/templates/oadrRegisteredReport.xml
openleadr/templates/oadrRequestEvent.xml
openleadr-0.5.30.dist-info/LICENSE
openleadr-0.5.30.dist-info/METADATA
openleadr-0.5.30.dist-info/WHEEL
openleadr-0.5.30.dist-info/entry_points.txt
openleadr-0.5.30.dist-info/top_level.txt
openleadr-0.5.30.dist-info/RECORD
