Metadata-Version: 2.1
Name: openleadr
Version: 0.5.30
Summary: Python3 library for building OpenADR Clients (VENs) and Servers (VTNs)
Home-page: https://openleadr.org
License: UNKNOWN
Project-URL: GitHub, https://github.com/openleadr/openleadr-python
Project-URL: Documentation, https://openleadr.org/docs
Platform: UNKNOWN
Requires-Python: >=3.7.0
Requires-Dist: aiohttp (<4.0.0,>=3.8.3)
Requires-Dist: apscheduler (<4.0.0,>=3.10.0)
Requires-Dist: jinja2 (<4.0.0,>=3.1.2)
Requires-Dist: signxml (<3.2.0,>=3.1.0)
Requires-Dist: xmltodict (==0.13.0)
